docs/mokkari/exceptions.md
docs/mokkari/session.md
docs/mokkari/sqlitecache.md
docs/mokkari/schemas/arc.md
docs/mokkari/schemas/base.md
docs/mokkari/schemas/character.md
docs/mokkari/schemas/collection.md
docs/mokkari/schemas/creator.md
docs/mokkari/schemas/generic.md
docs/mokkari/schemas/imprint.md
docs/mokkari/schemas/issue.md
docs/mokkari/schemas/publisher.md
docs/mokkari/schemas/reading_list.md
docs/mokkari/schemas/reprint.md
docs/mokkari/schemas/series.md
docs/mokkari/schemas/team.md
docs/mokkari/schemas/universe.md
docs/mokkari/schemas/user.md
docs/mokkari/schemas/variant.md
mokkari/__init__.py
mokkari/exceptions.py
mokkari/session.py
mokkari/sqlite_cache.py
mokkari/schemas/__init__.py
mokkari/schemas/arc.py
mokkari/schemas/base.py
mokkari/schemas/character.py
mokkari/schemas/collection.py
mokkari/schemas/creator.py
mokkari/schemas/generic.py
mokkari/schemas/imprint.py
mokkari/schemas/issue.py
mokkari/schemas/publisher.py
mokkari/schemas/reading_list.py
mokkari/schemas/reprint.py
mokkari/schemas/series.py
mokkari/schemas/team.py
mokkari/schemas/universe.py
mokkari/schemas/user.py
mokkari/schemas/variant.py
mokkari-3.17.0.dist-info/METADATA
mokkari-3.17.0.dist-info/WHEEL
mokkari-3.17.0.dist-info/licenses/LICENSE
mokkari-3.17.0.dist-info/RECORD
