Metadata-Version: 2.4
Name: mokkari
Version: 3.17.0
Summary: Python wrapper for Metron API
Project-URL: Homepage, https://github.com/Metron-Project/mokkari
Project-URL: Bug Tracker, https://github.com/Metron-Project/mokkari/issues
Author-email: Brian Pepple <bdpepple@gmail.com>
Maintainer-email: Brian Pepple <bdpepple@gmail.com>
License-Expression: GPL-3.0-or-later
License-File: LICENSE
Keywords: api,comic,comics,metadata,rest
Classifier: Development Status :: 5 - Production/Stable
Classifier: Environment :: Console
Classifier: Intended Audience :: Developers
Classifier: Natural Language :: English
Classifier: Operating System :: MacOS :: MacOS X
Classifier: Operating System :: Microsoft :: Windows
Classifier: Operating System :: POSIX
Classifier: Operating System :: POSIX :: BSD
Classifier: Operating System :: POSIX :: Linux
Classifier: Programming Language :: Python :: 3.10
Classifier: Programming Language :: Python :: 3.11
Classifier: Programming Language :: Python :: 3.12
Classifier: Programming Language :: Python :: 3.13
Classifier: Programming Language :: Python :: 3.14
Classifier: Topic :: Internet
Requires-Python: >=3.10
Requires-Dist: pydantic<3,>=2.10.3
Requires-Dist: pyrate-limiter<4,>=3.7.0
Requires-Dist: requests<3,>=2.26.0
